paydwrapper/__init__.py
paydwrapper/client.py
paydwrapper/models.py
paydwrapper-0.1.1.dist-info/licenses/LICENSE
paydwrapper-0.1.1.dist-info/METADATA
paydwrapper-0.1.1.dist-info/WHEEL
paydwrapper-0.1.1.dist-info/top_level.txt
paydwrapper-0.1.1.dist-info/RECORD
