Metadata-Version: 2.4
Name: paydwrapper
Version: 0.1.1
Summary: A python wrapper for Payd API payment integrations
Home-page: https://github.com/placesHQ/payd
Author: placesHQ
Author-email: "placeshq.com" <hello@placeshq.com>
License: MIT License
Keywords: payd,payments,api,wrapper,placeshq
Classifier: Programming Language :: Python :: 3
Classifier: License :: OSI Approved :: MIT License
Classifier: Operating System :: OS Independent
Requires-Python: >=3.8
License-File: LICENSE
Requires-Dist: requests
Dynamic: license-file
